{
    "building": "SML",
    "coordinate_1_indicator": "13",
    "coordinate_1_label": "Range",
    "coordinate_2_indicator": "c",
    "coordinate_2_label": "Section",
    "coordinate_3_indicator": "1",
    "coordinate_3_label": "Shelf",
    "create_time": "2015-06-01T15:49:14Z",
    "created_by": "admin",
    "external_ids": [
        {
            "create_time": "2018-10-31T16:51:55Z",
            "created_by": "amd243",
            "external_id": "1467",
            "jsonmodel_type": "external_id",
            "last_modified_by": "amd243",
            "source": "Archivists Toolkit Database::LOCATION",
            "system_mtime": "2018-10-31T16:51:55Z",
            "user_mtime": "2018-10-31T16:51:55Z"
        }
    ],
    "functions": [],
    "jsonmodel_type": "location",
    "last_modified_by": "amd243",
    "lock_version": 2,
    "room": "B70",
    "system_mtime": "2018-10-31T16:51:55Z",
    "title": "SML, B70 [Range: 13, Section: c, Shelf: 1]",
    "uri": "/locations/1550",
    "user_mtime": "2018-10-31T16:51:55Z"
}